{
    "name": "MHomeMarquee",
    "fields": [
        {
            "fieldName": "priority",
            "fieldType": "Integer",
            "fieldValidateRules": [
                "required"
            ]
        },
        {
            "fieldName": "marqueeText",
            "fieldType": "byte[]",
            "fieldTypeBlobContent": "text",
            "fieldValidateRules": [
                "required"
            ]
        },
        {
            "fieldName": "startAt",
            "fieldType": "Integer",
            "fieldValidateRules": [
                "required"
            ]
        },
        {
            "fieldName": "endAt",
            "fieldType": "Integer",
            "fieldValidateRules": [
                "required"
            ]
        }
    ],
    "relationships": [],
    "changelogDate": "20190611231010",
    "entityTableName": "m_home_marquee",
    "dto": "mapstruct",
    "pagination": "pagination",
    "service": "serviceClass",
    "jpaMetamodelFiltering": true,
    "fluentMethods": true,
    "clientRootFolder": "",
    "applications": "*"
}