{
    "name": "MLoginBonusRound",
    "fields": [
        {
            "fieldName": "roundId",
            "fieldType": "Integer",
            "fieldValidateRules": [
                "required"
            ]
        },
        {
            "fieldName": "bonusType",
            "fieldType": "Integer",
            "fieldValidateRules": [
                "required"
            ]
        },
        {
            "fieldName": "startAt",
            "fieldType": "Integer",
            "fieldValidateRules": [
                "required"
            ]
        },
        {
            "fieldName": "endAt",
            "fieldType": "Integer",
            "fieldValidateRules": [
                "required"
            ]
        },
        {
            "fieldName": "serifSanae",
            "fieldType": "byte[]",
            "fieldTypeBlobContent": "text",
            "fieldValidateRules": [
                "required"
            ]
        },
        {
            "fieldName": "serifYayoi",
            "fieldType": "byte[]",
            "fieldTypeBlobContent": "text",
            "fieldValidateRules": [
                "required"
            ]
        },
        {
            "fieldName": "serifYoshiko",
            "fieldType": "byte[]",
            "fieldTypeBlobContent": "text",
            "fieldValidateRules": [
                "required"
            ]
        },
        {
            "fieldName": "serifMaki",
            "fieldType": "byte[]",
            "fieldTypeBlobContent": "text",
            "fieldValidateRules": [
                "required"
            ]
        },
        {
            "fieldName": "sanaeImage",
            "fieldType": "byte[]",
            "fieldTypeBlobContent": "text"
        },
        {
            "fieldName": "yayoiImage",
            "fieldType": "byte[]",
            "fieldTypeBlobContent": "text"
        },
        {
            "fieldName": "yoshikoImage",
            "fieldType": "byte[]",
            "fieldTypeBlobContent": "text"
        },
        {
            "fieldName": "makiImage",
            "fieldType": "byte[]",
            "fieldTypeBlobContent": "text"
        },
        {
            "fieldName": "soundSwitchEventName",
            "fieldType": "byte[]",
            "fieldTypeBlobContent": "text",
            "fieldValidateRules": [
                "required"
            ]
        },
        {
            "fieldName": "nextId",
            "fieldType": "Integer"
        },
        {
            "fieldName": "lastDayAppealComment",
            "fieldType": "byte[]",
            "fieldTypeBlobContent": "text"
        },
        {
            "fieldName": "backgroundImage",
            "fieldType": "byte[]",
            "fieldTypeBlobContent": "text"
        }
    ],
    "relationships": [],
    "changelogDate": "20190611231021",
    "entityTableName": "m_login_bonus_round",
    "dto": "mapstruct",
    "pagination": "pagination",
    "service": "serviceClass",
    "jpaMetamodelFiltering": true,
    "fluentMethods": true,
    "clientRootFolder": "",
    "applications": "*"
}